odoo/addons/product_pricelist_alternative/README.rst
odoo/addons/product_pricelist_alternative/__init__.py
odoo/addons/product_pricelist_alternative/__manifest__.py
odoo/addons/product_pricelist_alternative/i18n/fr.po
odoo/addons/product_pricelist_alternative/i18n/it.po
odoo/addons/product_pricelist_alternative/i18n/product_pricelist_alternative.pot
odoo/addons/product_pricelist_alternative/models/__init__.py
odoo/addons/product_pricelist_alternative/models/product_pricelist.py
odoo/addons/product_pricelist_alternative/models/product_pricelist_item.py
odoo/addons/product_pricelist_alternative/readme/CONTRIBUTORS.rst
odoo/addons/product_pricelist_alternative/readme/DESCRIPTION.rst
odoo/addons/product_pricelist_alternative/static/description/icon.png
odoo/addons/product_pricelist_alternative/static/description/index.html
odoo/addons/product_pricelist_alternative/tests/__init__.py
odoo/addons/product_pricelist_alternative/tests/common.py
odoo/addons/product_pricelist_alternative/tests/test_pricelist_alternative.py
odoo/addons/product_pricelist_alternative/views/product_pricelist_item_view.xml
odoo/addons/product_pricelist_alternative/views/product_pricelist_view.xml
odoo_addon_product_pricelist_alternative-16.0.1.2.1.dist-info/METADATA
odoo_addon_product_pricelist_alternative-16.0.1.2.1.dist-info/WHEEL
odoo_addon_product_pricelist_alternative-16.0.1.2.1.dist-info/top_level.txt
odoo_addon_product_pricelist_alternative-16.0.1.2.1.dist-info/RECORD
